examples/__init__.py
examples/WIP/3.2_WIP_gravity_inversion.py
examples/WIP/__init__.py
examples/tutorials/__init__.py
examples/tutorials/0-intro/__init__.py
examples/tutorials/1-first_example_of_inference/__init__.py
examples/tutorials/1-first_example_of_inference/1-bayesian_basics/1.0_Overview_to_Bayesian_Inference.py
examples/tutorials/1-first_example_of_inference/1-bayesian_basics/1.1_Intro_to_Bayesian_Inference.py
examples/tutorials/1-first_example_of_inference/1-bayesian_basics/1.2_Intro_to_Bayesian_Inference.py
examples/tutorials/1-first_example_of_inference/1-bayesian_basics/1.3_Intro_to_Bayesian_Inference.py
examples/tutorials/1-first_example_of_inference/1-bayesian_basics/1.4_Intro_to_Bayesian_Inference.py
examples/tutorials/1-first_example_of_inference/1-bayesian_basics/__init__.py
examples/tutorials/1-first_example_of_inference/1-bayesian_basics/_aux_func.py
examples/tutorials/1-first_example_of_inference/2-next/__init__.py
examples/tutorials/2-basic_geology/1-thickness_problem.py
examples/tutorials/2-basic_geology/2-thickness_problem_gempy.py
examples/tutorials/2-basic_geology/__init__.py
examples/tutorials/2-basic_geology/1-prob_density_transformation/__init__.py
examples/tutorials/2-basic_geology/2-prob_density_gempy/__init__.py
examples/tutorials/2-basic_geology/next/__init__.py
examples/tutorials/3-probabilistic_inversion/3.1_FW_gravity.py
examples/tutorials/3-probabilistic_inversion/__init__.py
examples/tutorials/3-probabilistic_inversion/_aux_func.py
examples/tutorials/aux_functions/__init__.py
examples/utils/__init__.py
examples/utils/visual_scripting_I.py
gempy_probability/__init__.py
gempy_probability/_version.py
gempy_probability/aesara_op.py
gempy_probability/axes_utils.py
gempy_probability/decision_making.py
gempy_probability/fields.py
gempy_probability/joyplot.py
gempy_probability/plot_graphs.py
gempy_probability/plot_posterior.py
gempy_probability/posterior_analysis_DEP.py
gempy_probability/posterior_analysis_elisa.py
tests/__init__.py
gempy_probability-2024.1.1.dist-info/AUTHORS.rst
gempy_probability-2024.1.1.dist-info/LICENSE
gempy_probability-2024.1.1.dist-info/METADATA
gempy_probability-2024.1.1.dist-info/WHEEL
gempy_probability-2024.1.1.dist-info/top_level.txt
gempy_probability-2024.1.1.dist-info/RECORD
